koggi/__init__.py
koggi/__main__.py
koggi/cli.py
koggi/exceptions.py
koggi/pg.py
koggi/_bin/README.md
koggi/binaries/__init__.py
koggi/binaries/downloader.py
koggi/config/__init__.py
koggi/config/env_loader.py
koggi/config/init.py
koggi/database/__init__.py
koggi/database/backup.py
koggi/database/cleanup.py
koggi/database/connection.py
koggi/database/restore.py
koggi/ui/__init__.py
koggi/ui/backup_selector.py
koggi/utils/__init__.py
koggi-0.1.3.dist-info/METADATA
koggi-0.1.3.dist-info/WHEEL
koggi-0.1.3.dist-info/entry_points.txt
koggi-0.1.3.dist-info/licenses/LICENSE
koggi-0.1.3.dist-info/RECORD
