Metadata-Version: 2.4
Name: koggi
Version: 0.1.3
Summary: PostgreSQL backup & restore CLI
Project-URL: github, https://github.com/bamjun/koggi
Author-email: bamjun <khy5116@naver.com>
License: MIT
License-File: LICENSE
Keywords: backup,cli,postgresql,restore
Requires-Python: >=3.12
Requires-Dist: psycopg2-binary>=2.9.0
Requires-Dist: pydantic>=2.0.0
Requires-Dist: python-dotenv>=1.0.0
Requires-Dist: rich>=13.0.0
Requires-Dist: typer>=0.9.0
